mcp_commons/__init__.py
mcp_commons/adapters.py
mcp_commons/base.py
mcp_commons/bulk_registration.py
mcp_commons/config.py
mcp_commons/exceptions.py
mcp_commons/server.py
mcp_commons-1.3.2.dist-info/METADATA
mcp_commons-1.3.2.dist-info/WHEEL
mcp_commons-1.3.2.dist-info/top_level.txt
mcp_commons-1.3.2.dist-info/RECORD
