Metadata-Version: 2.4
Name: mcp-commons
Version: 1.3.2
Summary: Shared infrastructure library for MCP (Model Context Protocol) servers
Author: MCP Commons Contributors
License-Expression: MIT
Project-URL: Homepage, https://github.com/dawsonlp/mcp-commons
Project-URL: Repository, https://github.com/dawsonlp/mcp-commons.git
Project-URL: Documentation, https://github.com/dawsonlp/mcp-commons#readme
Project-URL: Issues, https://github.com/dawsonlp/mcp-commons/issues
Classifier: Development Status :: 4 - Beta
Classifier: Intended Audience :: Developers
Classifier: Programming Language :: Python :: 3
Classifier: Programming Language :: Python :: 3.11
Classifier: Programming Language :: Python :: 3.12
Classifier: Programming Language :: Python :: 3.13
Classifier: Topic :: Software Development :: Libraries :: Python Modules
Classifier: Topic :: Internet :: WWW/HTTP :: HTTP Servers
Requires-Python: >=3.11
Requires-Dist: pydantic>=2.12.5
Requires-Dist: PyYAML>=6.0.3
Requires-Dist: mcp>=1.23.2
Provides-Extra: dev
Requires-Dist: pytest>=9.0.2; extra == "dev"
Requires-Dist: pytest-asyncio>=1.3.0; extra == "dev"
Requires-Dist: pytest-cov>=7.0.0; extra == "dev"
Requires-Dist: black>=25.12.0; extra == "dev"
Requires-Dist: isort>=7.0.0; extra == "dev"
Requires-Dist: ruff>=0.14.8; extra == "dev"
